cuteuid/__init__.py
cuteuid/playground.py
cuteuid/preprocess.py
cuteuid/core/__init__.py
cuteuid/core/converters.py
cuteuid/core/kinds/__init__.py
cuteuid/core/kinds/base_uid.py
cuteuid/core/kinds/emoji_uid.py
cuteuid/core/kinds/leet_uid.py
cuteuid/data/emojis.json
cuteuid/data/words.json
src/cuteuid/__init__.py
cuteuid-1.0.1.dist-info/LICENSE
cuteuid-1.0.1.dist-info/METADATA
cuteuid-1.0.1.dist-info/WHEEL
cuteuid-1.0.1.dist-info/top_level.txt
cuteuid-1.0.1.dist-info/RECORD
