Metadata-Version: 2.1
Name: cuteuid
Version: 1.0.1
Summary: Generate cute UIDs, i.e. unique(ish) identifiers that are similar in appearance to UUIDs.
Home-page: https://github.com/alexdredmon/cuteuid
Author: Alex Redmon
Author-email: alexandriadredmon@gmail.com
License: UNKNOWN
Platform: UNKNOWN
Classifier: Programming Language :: Python :: 3
Classifier: License :: OSI Approved :: MIT License
Classifier: Operating System :: OS Independent
Requires-Python: >=3.6
